quicktake.py
quicktake-0.0.16.dist-info/LICENSE
quicktake-0.0.16.dist-info/METADATA
quicktake-0.0.16.dist-info/WHEEL
quicktake-0.0.16.dist-info/top_level.txt
quicktake-0.0.16.dist-info/RECORD
