Metadata-Version: 2.1
Name: quicktake
Version: 0.0.16
Summary: Off-the-shelf computer vision ML models. Yolov5, gender and age determination.
Author: Zach Wolpe
Author-email: zachcolinwolpe@gmail.com
Project-URL: Source code, https://github.com/ZachWolpe/QuickTake
Classifier: Programming Language :: Python :: 3
Classifier: License :: OSI Approved :: MIT License
Classifier: Operating System :: OS Independent
Requires-Python: >=3.8
License-File: LICENSE
Requires-Dist: torch >=2.0.1
Requires-Dist: torchvision >=0.15.2
Requires-Dist: torchviz >=0.0.2
Requires-Dist: tqdm >=4.66.1
Requires-Dist: pandas >=2.0.3
Requires-Dist: numpy >=1.24.3
Requires-Dist: opencv-python >=4.8.0
Requires-Dist: plotly >=5.16.1
Requires-Dist: plotly-express >=0.4.1
Requires-Dist: matplotlib >=3.7.2
Requires-Dist: pillow >=10.0.0
